eqc_direct/__init__.py
eqc_direct/client.py
eqc_direct/eqc_pb2.py
eqc_direct/eqc_pb2_grpc.py
eqc_direct/server_sim.py
eqc_direct/utils.py
eqc_direct-2.0.2.dist-info/METADATA
eqc_direct-2.0.2.dist-info/WHEEL
eqc_direct-2.0.2.dist-info/top_level.txt
eqc_direct-2.0.2.dist-info/RECORD
