Metadata-Version: 2.4
Name: eqc-direct
Version: 2.0.2
Summary: EQC GRPC client, and health tests
Author-email: "Quantum Computing Inc." <support@quantumcomputinginc.com>
Requires-Python: <3.11,>=3.9
Requires-Dist: grpcio==1.72.1
Requires-Dist: numpy<3,>=1.22.1
Requires-Dist: protobuf==3.20.3
Provides-Extra: dev
Requires-Dist: black<23,>=22.6.0; extra == "dev"
Requires-Dist: build<0.11.0,>=0.10.0; extra == "dev"
Requires-Dist: check-manifest<0.49,>=0.48; extra == "dev"
Requires-Dist: coverage[toml]<7,>=6.4.2; extra == "dev"
Requires-Dist: eqc_direct[sim]; extra == "dev"
Requires-Dist: grpcio-tools==1.48.2; extra == "dev"
Requires-Dist: pylint<3,>=2.14.0; extra == "dev"
Requires-Dist: pytest<8,>=7.1.0; extra == "dev"
Requires-Dist: sphinx-rtd-theme<2,>=1.3.0; extra == "dev"
Provides-Extra: sim
Requires-Dist: multiprocess<1,>=0.70.14; extra == "sim"
